unimeta/__init__.py
unimeta/event.py
unimeta/fake.py
unimeta/metaserver.py
unimeta/model.py
unimeta/mysql2ch.py
unimeta/pipeline.py
unimeta/table.py
unimeta/libs/__init__.py
unimeta/libs/libformat.py
unimeta/libs/liburl.py
unimeta-0.2.8.dist-info/LICENSE-APACHE
unimeta-0.2.8.dist-info/LICENSE-MIT
unimeta-0.2.8.dist-info/METADATA
unimeta-0.2.8.dist-info/WHEEL
unimeta-0.2.8.dist-info/top_level.txt
unimeta-0.2.8.dist-info/RECORD
