Metadata-Version: 2.1
Name: unimeta
Version: 0.2.8
Summary: UNKNOWN
Home-page: https://github.com/kulame/unimeta
Author: kula
Author-email: kula@live.com
Maintainer: kula
Maintainer-email: kula@live.com
License: MIT/Apache-2.0
Platform: UNKNOWN
Classifier: Development Status :: 4 - Beta
Classifier: Intended Audience :: Developers
Classifier: License :: OSI Approved :: MIT License
Classifier: License :: OSI Approved :: Apache Software License
Classifier: Natural Language :: English
Classifier: Operating System :: OS Independent
Classifier: Programming Language :: Python :: 3.7
Classifier: Programming Language :: Python :: 3.8
Classifier: Programming Language :: Python :: Implementation :: CPython
Requires-Dist: devtools
Requires-Dist: mysql-replication
Requires-Dist: pydantic
Requires-Dist: loguru
Requires-Dist: sqlalchemy
Requires-Dist: faker
Requires-Dist: databases
Requires-Dist: clickhouse-driver
Requires-Dist: mysqlclient
Requires-Dist: fastapi
Requires-Dist: uvicorn
Requires-Dist: aiokafka
Requires-Dist: aioch
Requires-Dist: aiohttp
